{
  "course_id": "res-6-012-introduction-to-probability-spring-2018",
  "course_title": "Introduction to Probability",
  "course_image_url": "https://open-learning-course-data-production.s3.amazonaws.com/res-6-012-introduction-to-probability-spring-2018/15f66b6f0289f4b4f3e9577b7c264182_res-6-012s18.jpg",
  "course_thumbnail_image_url": "https://open-learning-course-data-production.s3.amazonaws.com/res-6-012-introduction-to-probability-spring-2018/af381783ee49d0c853367ba46bdf21bc_res-6-012s18-th.jpg",
  "course_image_alternate_text": "Graphic showing the connections between probability theory, inference and statistics, and the real world.",
  "course_image_caption_text": "<p>The role of probability theory is to provide a framework for analyzing phenomena with uncertain outcomes. (Image by John Tsitsiklis.)</p>",
  "publishdate": "2018-04-24T12:20:56-04:00",
  "instructors": [
    {
      "instructor": "Patrick Jaillet",
      "url": "/search/?q=%22Patrick%20Jaillet%22"
    },
    {
      "instructor": "John Tsitsiklis",
      "url": "/search/?q=%22John%20Tsitsiklis%22"
    }
  ],
  "departments": [
    {
      "department": "Supplemental Resources",
      "url": "/search/?d=Supplemental%20Resources"
    }
  ],
  "course_features": [
    {
      "feature": "Lecture Videos",
      "url": "/sections/part-i-the-fundamentals"
    },
    {
      "feature": "Lecture Notes",
      "url": "/sections/part-i-the-fundamentals"
    }
  ],
  "topics": [
    {
      "topic": "Engineering",
      "subtopics": [
        {
          "subtopic": "Systems Engineering",
          "specialities": [],
          "url": "/search/?t=Systems%20Engineering"
        }
      ],
      "url": "/search/?t=Engineering"
    },
    {
      "topic": "Mathematics",
      "subtopics": [
        {
          "subtopic": "Probability and Statistics",
          "specialities": [],
          "url": "/search/?t=Probability%20and%20Statistics"
        }
      ],
      "url": "/search/?t=Mathematics"
    }
  ],
  "course_numbers": [
    "RES.6-012"
  ],
  "term": "Spring 2018",
  "level": {
    "level": "Undergraduate",
    "url": "/search/?l=Undergraduate"
  },
  "other_versions": [],
  "open_learning_library_versions": []
}